MANIFEST.in
README.rst
setup.py
asynctask/__init__.py
asynctask/celery.py
asynctask/db.py
asynctask/proxy.py
asynctask/setting.py
asynctask.egg-info/PKG-INFO
asynctask.egg-info/SOURCES.txt
asynctask.egg-info/dependency_links.txt
asynctask.egg-info/requires.txt
asynctask.egg-info/top_level.txt
asynctask/cron/__init__.py
asynctask/lib/__init__.py
asynctask/unit/__init__.py
asynctask/zerorpc/__init__.py
asynctask/zerorpc/client.py
asynctask/zerorpc/server.py