Metadata-Version: 1.0
Name: asynctask
Version: 0.0.3
Summary: wecatch asynctask
Home-page: https://github.com/listen-lavender/asynctask
Author: haokuan
Author-email: jingdaohao@gmail.com
License: UNKNOWN
Keywords: wecatch >
Platform: UNKNOWN
